xyxABC785/__init__.py
xyxABC785/xyxABC785.py
xyxABC785-0.1.1.dist-info/AUTHORS.rst
xyxABC785-0.1.1.dist-info/LICENSE
xyxABC785-0.1.1.dist-info/METADATA
xyxABC785-0.1.1.dist-info/WHEEL
xyxABC785-0.1.1.dist-info/top_level.txt
xyxABC785-0.1.1.dist-info/RECORD
