Metadata-Version: 2.1
Name: xyxABC785
Version: 0.1.1
Summary: just testing, how to upload the package
Home-page: https://github.com/abcXyz/xyxABC785
Author: abcXyz
Author-email: xyz@gmail.com
License: MIT license
Keywords: xyxABC785
Classifier: Development Status :: 2 - Pre-Alpha
Classifier: Intended Audience :: Developers
Classifier: License :: OSI Approved :: MIT License
Classifier: Natural Language :: English
Classifier: Programming Language :: Python :: 3
Classifier: Programming Language :: Python :: 3.6
Classifier: Programming Language :: Python :: 3.7
Classifier: Programming Language :: Python :: 3.8
Requires-Python: >=3.6
License-File: LICENSE
License-File: AUTHORS.rst
